bash_menu_builder/__init__.py
bash_menu_builder/abstract_menu.py
bash_menu_builder/color.py
bash_menu_builder/draw.py
bash_menu_builder/input_menu.py
bash_menu_builder/message.py
bash_menu_builder/select_menu.py
bash_menu_builder-1.1.5.dist-info/LICENSE
bash_menu_builder-1.1.5.dist-info/METADATA
bash_menu_builder-1.1.5.dist-info/WHEEL
bash_menu_builder-1.1.5.dist-info/top_level.txt
bash_menu_builder-1.1.5.dist-info/RECORD
